{
  "schemaVersion": 1,
  "generatedAt": "2026-02-26T03:35:45.913Z",
  "windowHours": 168,
  "assessedSessionCount": 2,
  "regressionSessionCount": 0,
  "investigateSessionCount": 0,
  "meanRegressionScore": 0,
  "maxRegressionScore": 0,
  "entries": [
    {
      "sessionId": "sess-int-02",
      "runId": "sess-int-02",
      "status": "closed",
      "runtime": "unavailable",
      "updatedAt": "2026-02-26T03:35:45.910Z",
      "actionCount": 1515,
      "artifactCount": 0,
      "failureCount": 759,
      "regressionScore": 0,
      "regressionSignal": "none",
      "regressionPairCount": 0
    },
    {
      "sessionId": "sess-int-03",
      "runId": "sess-int-03",
      "status": "closed",
      "runtime": "unavailable",
      "updatedAt": "2026-02-26T03:35:45.778Z",
      "actionCount": 803,
      "artifactCount": 0,
      "failureCount": 536,
      "regressionScore": 0,
      "regressionSignal": "none",
      "regressionPairCount": 0
    }
  ]
}
