{
  "schemaVersion": 1,
  "generatedAt": "2026-02-26T04:05:13.696Z",
  "windowHours": 168,
  "assessedSessionCount": 2,
  "regressionSessionCount": 0,
  "investigateSessionCount": 0,
  "meanRegressionScore": 0,
  "maxRegressionScore": 0,
  "entries": [
    {
      "sessionId": "sess-int-03",
      "runId": "sess-int-03",
      "status": "closed",
      "runtime": "unavailable",
      "updatedAt": "2026-02-26T03:52:23.144Z",
      "actionCount": 917,
      "artifactCount": 0,
      "failureCount": 610,
      "regressionScore": 0,
      "regressionSignal": "none",
      "regressionPairCount": 0
    },
    {
      "sessionId": "sess-int-02",
      "runId": "sess-int-02",
      "status": "closed",
      "runtime": "unavailable",
      "updatedAt": "2026-02-26T03:52:22.977Z",
      "actionCount": 1570,
      "artifactCount": 0,
      "failureCount": 785,
      "regressionScore": 0,
      "regressionSignal": "none",
      "regressionPairCount": 0
    }
  ]
}
